cyberfusion/PowerDNSSecondaryCleaner/CLI.py
cyberfusion/PowerDNSSecondaryCleaner/__init__.py
cyberfusion/PowerDNSSecondaryCleaner/powerdns_api.py
powerdns_secondary_cleaner-1.0.4.1.dist-info/METADATA
powerdns_secondary_cleaner-1.0.4.1.dist-info/WHEEL
powerdns_secondary_cleaner-1.0.4.1.dist-info/entry_points.txt
powerdns_secondary_cleaner-1.0.4.1.dist-info/top_level.txt
powerdns_secondary_cleaner-1.0.4.1.dist-info/RECORD
