Metadata-Version: 2.1
Name: powerdns-secondary-cleaner
Version: 1.0.4.1
Summary: Use powerdns-secondary-cleaner to delete zones on secondary PowerDNS server that were deleted on primary PowerDNS server.
Author-email: Cyberfusion <support@cyberfusion.io>
Project-URL: Source, https://github.com/CyberfusionIO/powerdns-secondary-cleaner
Requires-Dist: docopt ==0.6.2
Requires-Dist: schema ==0.7.7
Requires-Dist: requests ==2.32.3
